<annotation>
	<folder>0325待标注</folder>
	<filename>LXCH511FDRA-200325065045375-1-qMQkz.jpg</filename>
	<path>C:\Users\Umika\Desktop\0325待标注\LXCH511FDRA-200325065045375-1-qMQkz.jpg</path>
	<source>
		<database>Unknown</database>
	</source>
	<size>
		<width>1280</width>
		<height>720</height>
		<depth>3</depth>
	</size>
	<segmented>0</segmented>
	<object>
		<name>goods</name>
		<pose>Unspecified</pose>
		<truncated>0</truncated>
		<difficult>0</difficult>
		<bndbox>
			<xmin>350</xmin>
			<ymin>79</ymin>
			<xmax>430</xmax>
			<ymax>180</ymax>
		</bndbox>
	</object>
	<object>
		<name>goods</name>
		<pose>Unspecified</pose>
		<truncated>0</truncated>
		<difficult>0</difficult>
		<bndbox>
			<xmin>492</xmin>
			<ymin>69</ymin>
			<xmax>583</xmax>
			<ymax>161</ymax>
		</bndbox>
	</object>
	<object>
		<name>goods</name>
		<pose>Unspecified</pose>
		<truncated>0</truncated>
		<difficult>0</difficult>
		<bndbox>
			<xmin>898</xmin>
			<ymin>128</ymin>
			<xmax>989</xmax>
			<ymax>231</ymax>
		</bndbox>
	</object>
</annotation>